{
  "2": [
    "Алгебра",
    "Химия",
    "Каз.литер",
    "Каз.язык",
    "Физика",
    "Биология",
    "История Казахстана",
    "Алгебра"
  ],
  "3": [
    "Геометрия",
    "География",
    "История Казахстана",
    "Технология",
    "Каз.язык",
    "Русская литература",
    "Англ.язык",
    "Физкультура",
    "Религиоведение"
  ],
  "4": [
    "Каз.язык",
    "Химия",
    "Физика",
    "Черчение",
    "ОИВТ",
    "Русская литература",
    "Самопознание",
    "Химия ДСК"
  ],
  "5": [
    "Биология",
    "Алгебра",
    "Каз.язык",
    "Русский язык",
    "Англ.язык",
    "География",
    "Химия",
    "Физкультура"
  ],
  "6": [
    "Русский язык",
    "Геометрия",
    "Физкультура",
    "Черчение",
    "Химия",
    "Физ.практ",
    "Всемирная история",
    "ЧОП"
  ],
  "7": [],
  "1": []
}